{
  "resourceType" : "Observation",
  "id" : "SleepObservationExample",
  "meta" : {
    "profile" : ["http://hl7.dk/fhir/hackathons/StructureDefinition/SleepObservation"]
  },
  "text" : {
    "status" : "extensions",
    "div" : "<div xmlns=\"http://www.w3.org/1999/xhtml\"><p class=\"res-header-id\"><b>Generated Narrative: Observation SleepObservationExample</b></p><a name=\"SleepObservationExample\"> </a><a name=\"hcSleepObservationExample\"> </a><div style=\"display: inline-block; background-color: #d9e0e7; padding: 6px; margin: 4px; border: 1px solid #8da1b4; border-radius: 5px; line-height: 60%\"><p style=\"margin-bottom: 0px\"/><p style=\"margin-bottom: 0px\">Profile: <a href=\"StructureDefinition-SleepObservation.html\">SleepObservation</a></p></div><p><b>Episode of care</b>: <a href=\"EpisodeOfCare-EpisodeOfCareExample.html\">EpisodeOfCare: status = active; period = 2022-09-01 00:00:00+0200 --&gt; (ongoing)</a></p><p><b>status</b>: Final</p><p><b>code</b>: <span title=\"Codes:{http://snomed.info/sct 248263006}\">Duration of sleep</span></p><p><b>subject</b>: <a href=\"Patient-PatientExample.html\">Nancy Ann Berggren (official) Unknown, DoB Unknown ( urn:oid:1.2.208.176.1.2#DK Central Person Registry (CPR)#2512489996\u00a0(use:\u00a0official,\u00a0))</a></p><p><b>effective</b>: 2022-09-05 12:00:00+0200 --&gt; 2022-09-06 12:00:00+0200</p><p><b>performer</b>: <a href=\"Patient-PatientExample.html\">Nancy Ann Berggren (official) Unknown, DoB Unknown ( urn:oid:1.2.208.176.1.2#DK Central Person Registry (CPR)#2512489996\u00a0(use:\u00a0official,\u00a0))</a></p><p><b>value</b>: 5</p></div>"
  },
  "extension" : [{
    "url" : "http://hl7.org/fhir/StructureDefinition/workflow-episodeOfCare",
    "valueReference" : {
      "reference" : "EpisodeOfCare/EpisodeOfCareExample"
    }
  }],
  "status" : "final",
  "code" : {
    "coding" : [{
      "system" : "http://snomed.info/sct",
      "code" : "248263006"
    }]
  },
  "subject" : {
    "reference" : "Patient/PatientExample"
  },
  "effectivePeriod" : {
    "start" : "2022-09-05T12:00:00+02:00",
    "end" : "2022-09-06T12:00:00+02:00"
  },
  "performer" : [{
    "reference" : "Patient/PatientExample"
  }],
  "valueQuantity" : {
    "value" : 5
  }
}